mkdocs-src-links-corrector/__init__.py
mkdocs-src-links-corrector/plugin.py
mkdocs_src_links_corrector/__init__.py
mkdocs_src_links_corrector/plugin.py
mkdocs_src_links_corrector-0.0.3.dist-info/METADATA
mkdocs_src_links_corrector-0.0.3.dist-info/WHEEL
mkdocs_src_links_corrector-0.0.3.dist-info/entry_points.txt
mkdocs_src_links_corrector-0.0.3.dist-info/top_level.txt
mkdocs_src_links_corrector-0.0.3.dist-info/RECORD
