Metadata-Version: 2.1
Name: mkdocs-src-links-corrector
Version: 0.0.3
Summary: An MkDocs plugin
Home-page: https://github.com/barmidrol/mkdocs-src-links-corrector
Author: Siarhei Padlozny
Author-email: barmidrol@gmail.com
License: MIT
Keywords: mkdocs
Classifier: Development Status :: 4 - Beta
Classifier: Intended Audience :: Developers
Classifier: Intended Audience :: Information Technology
Classifier: License :: OSI Approved :: MIT License
Classifier: Programming Language :: Python
Classifier: Programming Language :: Python :: 3 :: Only
Classifier: Programming Language :: Python :: 3.4
Classifier: Programming Language :: Python :: 3.5
Classifier: Programming Language :: Python :: 3.6
Classifier: Programming Language :: Python :: 3.7
Requires-Python: >=3.4
Requires-Dist: mkdocs >=1.2.3
